arcor2_fanuc/VERSION
arcor2_fanuc/__init__.py
arcor2_fanuc/exceptions.py
arcor2_fanuc/py.typed
arcor2_fanuc/scripts/__init__.py
arcor2_fanuc/scripts/fanuc.py
arcor2_fanuc-0.4.0.dist-info/METADATA
arcor2_fanuc-0.4.0.dist-info/WHEEL
arcor2_fanuc-0.4.0.dist-info/entry_points.txt
arcor2_fanuc-0.4.0.dist-info/namespace_packages.txt
arcor2_fanuc-0.4.0.dist-info/top_level.txt
arcor2_fanuc-0.4.0.dist-info/RECORD
