Metadata-Version: 2.1
Name: arcor2-fanuc
Version: 0.4.0
Summary: ARCOR2 Fanuc Service
Author: Robo@FIT
Author-email: imaterna@fit.vut.cz
License: LGPL
Classifier: Development Status :: 3 - Alpha
Classifier: Intended Audience :: Developers
Classifier: Topic :: Software Development :: Build Tools
Classifier: License :: OSI Approved :: GNU Lesser General Public License v3 (LGPLv3)
Classifier: Programming Language :: Python :: 3.11
Classifier: Natural Language :: English
Classifier: Topic :: Scientific/Engineering
Requires-Python: ==3.11.*
Requires-Dist: Flask (~=3.0.2)
Requires-Dist: arcor2 (~=1.3.0)
Requires-Dist: fanucpy (~=0.1.14)
Requires-Dist: requests (~=2.31.0)
Requires-Dist: types-requests (==2.31.0.20240311)
